pjfeedreader/__init__.py
pjfeedreader/models.py
pjfeedreader/urls.py
pjfeedreader/views.py
pjfeedreader/serializers.py
pjfeedreader/exception_logging_middleware.py
pjfeedreader/admin.py
pjfeedreader/migrations/0001_initial.py
pjfeedreader/migrations/0002_auto_20151023_1210.py
pjfeedreader/migrations/__init__.py
pjfeedreader/static/css/pjfeedreader.css
pjfeedreader/static/js/pj-reader.routes.js
pjfeedreader/static/js/pjfeedreader.js
pjfeedreader/static/js/feeds/feeds.module.js
pjfeedreader/static/js/feeds/controllers/about.js
pjfeedreader/static/js/feeds/controllers/categories.controller.js
pjfeedreader/static/js/feeds/controllers/new-feed.controller.js
pjfeedreader/static/js/feeds/services/categories.service.js
pjfeedreader/static/js/feeds/services/feeds.service.js
pjfeedreader/static/js/layout/pjfeedreader.layout.module.js
pjfeedreader/static/js/layout/controllers/index.controller.js
pjfeedreader/static/templates/feeds/new-feed.html
pjfeedreader/static/templates/layout/koe.html
pjfeedreader/static/templates/layout/main.html
pjfeedreader/static/vendor/bower_components/bootstrap-material-design/Gruntfile.js
pjfeedreader/static/vendor/bower_components/bootstrap-material-design/bootstrap-elements.html
pjfeedreader/static/vendor/bower_components/bootstrap-material-design/package.js
pjfeedreader/static/vendor/bower_components/bootstrap-material-design/dist/test.html
pjfeedreader/static/vendor/bower_components/bootstrap-material-design/dist/css/material-fullpalette.css
pjfeedreader/static/vendor/bower_components/bootstrap-material-design/dist/css/material-fullpalette.min.css
pjfeedreader/static/vendor/bower_components/bootstrap-material-design/dist/css/material.css
pjfeedreader/static/vendor/bower_components/bootstrap-material-design/dist/css/material.min.css
pjfeedreader/static/vendor/bower_components/bootstrap-material-design/dist/css/ripples.css
django_pj_feedreader-0.1.2.dist-info/top_level.txt
django_pj_feedreader-0.1.2.dist-info/METADATA
django_pj_feedreader-0.1.2.dist-info/DESCRIPTION.rst
django_pj_feedreader-0.1.2.dist-info/metadata.json
django_pj_feedreader-0.1.2.dist-info/WHEEL
django_pj_feedreader-0.1.2.dist-info/RECORD
