Metadata-Version: 2.0
Name: django-pj-feedreader
Version: 0.1.2
Summary: Django/AngularJS RSS feed reader
Home-page: https://github.com/jokimies/django-pj-feedreader
Author: Petri Jokimies
Author-email: petri.jokimies@gmail.com
License: BSD
Keywords: django-pj-feedreader
Platform: UNKNOWN
Classifier: Development Status :: 3 - Alpha
Classifier: Framework :: Django
Classifier: Intended Audience :: Developers
Classifier: License :: OSI Approved :: BSD License
Classifier: Natural Language :: English
Classifier: Programming Language :: Python :: 2
Classifier: Programming Language :: Python :: 2.7
Classifier: Programming Language :: Python :: 3
Classifier: Programming Language :: Python :: 3.3
Classifier: Programming Language :: Python :: 3.4
